{
  "id": "garden-bar",
  "name": "Garden Bar",
  "url": "https://www.facebook.com/126626397494420",
  "phone": "+48 691 409 510",
  "scrapedAt": "2026-07-03T11:22:49.867Z",
  "menus": [
    {
      "date": "2026-07-03",
      "items": [
        {
          "name": "Filet z morszczuka w panierce, młode ziemniaki lub frytki, surówki lub kiszona zasmażana (Zestaw dnia)",
          "price": 34
        },
        {
          "name": "Pieczarkowa",
          "price": 8
        }
      ]
    },
    {
      "date": "2026-07-02",
      "items": [
        {
          "name": "Filet z udźca kurczaka po hawajsku zapiekany z ananasem i serem plus żurawina (Danie na czwartek)",
          "price": 25
        },
        {
          "name": "Ogórkowa z ryżem",
          "price": 8
        }
      ]
    },
    {
      "date": "2026-07-01",
      "items": [
        {
          "name": "Kotlet drobiowy szarpany smażony w cieście z warzywami, frytki lub ziemniaki, surówki lub słodka kapusta zasmażana (Oferta dnia)",
          "price": 25
        },
        {
          "name": "Kapuśniak z ziemniakami",
          "price": 8
        }
      ]
    },
    {
      "date": "2026-06-30",
      "items": [
        {
          "name": "Kotlet wieprzowy mielony, ziemniaki i marchewka z groszkiem (Oferta na wtorek)",
          "price": 25
        },
        {
          "name": "Krem warzywny z grzanką",
          "price": 8
        }
      ]
    }
  ]
}
